mcpgateway_client/__init__.py
mcpgateway_client/__main__.py
mcpgateway_client/cli.py
mcpgateway_client/client_websocket.py
mcpgateway_client/types.py
mcpgateway_client/utils.py
mcpgateway_client-0.1.6.dist-info/METADATA
mcpgateway_client-0.1.6.dist-info/WHEEL
mcpgateway_client-0.1.6.dist-info/entry_points.txt
mcpgateway_client-0.1.6.dist-info/licenses/LICENSE
mcpgateway_client-0.1.6.dist-info/RECORD
