Metadata-Version: 2.4
Name: mcpgateway-client
Version: 0.1.6
Summary: A lightweight SnapEnv McpGateway client for SnapEnv McpGateway server, enabling AI Agents access to MCP server's running on local computer.
Project-URL: Homepage, https://snapby.github.io/mcpgateway-client/
Project-URL: Repository, https://github.com/snapby/mcpgateway-client
Project-URL: Documentation, https://snapby.github.io/mcpgateway-client/
Author-email: Abner G Jacobsen <admin@h100.com.br>
License-File: LICENSE
Keywords: python
Classifier: Intended Audience :: Developers
Classifier: Programming Language :: Python
Classifier: Programming Language :: Python :: 3
Classifier: Programming Language :: Python :: 3.9
Classifier: Programming Language :: Python :: 3.10
Classifier: Programming Language :: Python :: 3.11
Classifier: Programming Language :: Python :: 3.12
Classifier: Programming Language :: Python :: 3.13
Classifier: Topic :: Software Development :: Libraries :: Python Modules
Requires-Python: <4.0,>=3.11
Requires-Dist: typer>=0.15.3
Requires-Dist: websockets>=15.0.1
